[
  {
    "public_id": "u_3s93ff2esdao",
    "exported_at": "2026-04-16T23:46:30+09:00",
    "crew_id": "79971038",
    "player_name": "あんこきじ",
    "paskill_average_top30": 15.5003,
    "privacy": {
      "search_user": true,
      "player_name": true,
      "crew_id": true,
      "paskill": true
    }
  },
  {
    "public_id": "u_aq1lykfqps8v",
    "exported_at": "2026-04-16T22:47:03+09:00",
    "crew_id": "32474862",
    "player_name": "えば",
    "paskill_average_top30": 15.9472,
    "privacy": {
      "search_user": true,
      "player_name": true,
      "crew_id": true,
      "paskill": true
    }
  },
  {
    "public_id": "u_va4pyrb7dhgs",
    "exported_at": "2026-04-15T23:16:03+09:00",
    "crew_id": "56675311",
    "player_name": "ひなの",
    "paskill_average_top30": 15.7997,
    "privacy": {
      "search_user": true,
      "player_name": true,
      "crew_id": true,
      "paskill": true
    }
  },
  {
    "public_id": "u_x7eyy2al62j9",
    "exported_at": "2026-04-14T10:39:55+09:00",
    "crew_id": "10615451",
    "player_name": "ｓｐａｄｅ",
    "paskill_average_top30": 16.0182,
    "privacy": {
      "search_user": true,
      "player_name": true,
      "crew_id": true,
      "paskill": true
    }
  },
  {
    "public_id": "u_yupszniqxe39",
    "exported_at": "2026-04-14T00:22:12+09:00",
    "crew_id": "32071900",
    "player_name": "Ｔｓｕｋａｎａ",
    "paskill_average_top30": 16.0572,
    "privacy": {
      "search_user": true,
      "player_name": true,
      "crew_id": true,
      "paskill": true
    }
  },
  {
    "public_id": "u_ec17osb9za99",
    "exported_at": "2026-04-13T22:21:40+09:00",
    "crew_id": "68207041",
    "player_name": "さまよい",
    "paskill_average_top30": 16.0134,
    "privacy": {
      "search_user": true,
      "player_name": true,
      "crew_id": true,
      "paskill": true
    }
  },
  {
    "public_id": "u_k3leep72ejni",
    "exported_at": "2026-04-13T21:20:25+09:00",
    "crew_id": "32891845",
    "player_name": "ぱげ",
    "paskill_average_top30": 13.8168,
    "privacy": {
      "search_user": true,
      "player_name": true,
      "crew_id": true,
      "paskill": true
    }
  },
  {
    "exported_at": "2026-04-06T22:11:59+09:00",
    "crew_id": "17365817",
    "player_name": "ＱＵ４ＲＴＺ",
    "title_name": "初めまして",
    "pa_skill": 14.92,
    "pa_class": 81,
    "play_count": 54,
    "paskill_average_top30": 14.8981,
    "privacy": {
      "search_user": true,
      "player_name": true,
      "crew_id": true,
      "paskill": true
    }
  }
]