{
  "public_id": "u_82feit151f2n",
  "crew_id": "34229664",
  "player_name": "ＫＴ！？！",
  "has_diff": true,
  "updated_music_count": 2,
  "summary": {
    "pa_class": {
      "before": 486,
      "after": 487
    },
    "play_count": {
      "before": 2335,
      "after": 2346
    },
    "paskill_average_top30": {
      "before": 15.9308,
      "after": 15.9308
    }
  },
  "updated_music_list": [
    {
      "music_id": "8b5d41f5f3c44025ef0f7790cd4aec19",
      "music_title": "Squeeze",
      "diff": "inf",
      "level": 12,
      "level_disp": "12+",
      "jacket_url": "https://p.eagate.573.jp/game/polarischord/pc/img/music/jacket.html?c=8b5d41f5f3c44025ef0f7790cd4aec19",
      "ar_before": 9993,
      "ar_after": 10000,
      "clear_status_before": "full",
      "clear_status_after": "perfect",
      "ar_changed": true,
      "clear_status_changed": true
    },
    {
      "music_id": "410e01f01bec2e7a619960a1cbbca6c8",
      "music_title": "漆黒のスペシャルプリンセスサンデー",
      "diff": "inf",
      "level": 12,
      "level_disp": "12+",
      "jacket_url": "https://p.eagate.573.jp/game/polarischord/pc/img/music/jacket.html?c=410e01f01bec2e7a619960a1cbbca6c8",
      "ar_before": 9998,
      "ar_after": 10000,
      "clear_status_before": "full",
      "clear_status_after": "perfect",
      "ar_changed": true,
      "clear_status_changed": true
    }
  ],
  "exported_at": "2026-04-18T12:04:01+09:00",
  "is_initial": false,
  "diff_summary": "player.title_name:DISTORDER LOVE！！！=>綿間瀬 わたこ 極, player.pa_class:486=>487, player.play_count:2335=>2346, 8b5d41f5f3c44025ef0f7790cd4aec19__inf.ar:9993=>10000, 8b5d41f5f3c44025ef0f7790cd4aec19__inf.clear_status:full=>perfect, 410e01f01bec2e7a619960a1cbbca6c8__inf.ar:9998=>10000, 410e01f01bec2e7a619960a1cbbca6c8__inf.clear_status:full=>perfect",
  "latest_path": "data/users/34229664.json",
  "history_path": "data/history/34229664/2026-04-18T12-04-01plus09-00.json",
  "saved_at": "2026-04-18T12:04:09+09:00"
}